optommp/O22SIOUT.py
optommp/__init__.py
optommp-0.7.dist-info/licenses/LICENSE.txt
optommp-0.7.dist-info/METADATA
optommp-0.7.dist-info/WHEEL
optommp-0.7.dist-info/top_level.txt
optommp-0.7.dist-info/RECORD
