Metadata-Version: 2.4
Name: optommp
Version: 0.7
Summary: Python toolkit for Opto 22 memory-mapped devices
Home-page: http://github.com/optodeveloper/optommp
Download-URL: https://github.com/optodeveloper/optommp/archive/refs/tags/v0.7.tar.gz
Author: Opto 22
Author-email: developer@opto22.com
License: mit
Classifier: License :: OSI Approved :: MIT License
Classifier: Programming Language :: Python :: 3.10
License-File: LICENSE.txt
Dynamic: author
Dynamic: author-email
Dynamic: classifier
Dynamic: description
Dynamic: download-url
Dynamic: home-page
Dynamic: license
Dynamic: license-file
Dynamic: summary
